{
  "total_papers": 18560,
  "total_authors": 66710,
  "total_topics": 5308,
  "total_gaps": 101,
  "total_labs": 16,
  "total_universities": 24,
  "papers_by_venue": {
    "EMNLP": 1520,
    "ICLR": 2678,
    "ACL": 1448,
    "AAAI": 65,
    "Findings": 1329,
    "COLING": 202,
    "COLM": 113,
    "NeurIPS": 1743,
    "CVPR": 147,
    "EACL": 244,
    "ICCV": 49,
    "arXiv": 8352,
    "NAACL": 526,
    "TACL": 43,
    "IJCAI": 54,
    "CHI": 47
  },
  "papers_by_source": {
    "acl_anthology": 5312,
    "openreview": 4534,
    "semantic_scholar": 166,
    "cvf": 196,
    "arxiv": 8352
  },
  "difficulty_distribution": {
    "L1": 6174,
    "L4": 1533,
    "L3": 4955,
    "L2": 5898
  },
  "paper_type_distribution": {
    "benchmark": 3506,
    "methods": 9141,
    "dataset": 3302,
    "systems": 1507,
    "theory": 688,
    "position": 173,
    "empirical": 43,
    "negative_result": 132,
    "survey": 62,
    "tutorial": 2,
    "replication": 4
  },
  "papers_by_year": {
    "1981": 1,
    "2015": 1,
    "2016": 3,
    "2017": 1,
    "2019": 2,
    "2020": 60,
    "2021": 171,
    "2022": 425,
    "2023": 1470,
    "2024": 3067,
    "2025": 4727,
    "2026": 8632
  },
  "gaps_by_type": {
    "starter": 34,
    "pattern": 10,
    "explicit": 57
  },
  "generated_at": "2026-05-25T07:38:04.237098+00:00"
}